dtlapse/__init__.py
dtlapse/dtlapse.py
dtlapse/xcoder.py
dtlapse/args/__init__.py
dtlapse/args/help.py
dtlapse/args/parser.py
dtlapse/iops/bilat.json
dtlapse/iops/colorbalance.json
dtlapse/iops/demosaic.json
dtlapse/iops/exposure.json
dtlapse/iops/filmicrgb.json
dtlapse/iops/graduatednd.json
dtlapse/iops/hazeremoval.json
dtlapse/iops/highlights.json
dtlapse/iops/hotpixels.json
dtlapse/iops/lens.json
dtlapse/iops/rgbcurve.json
dtlapse/iops/temperature.json
dtlapse/iops/toneequal.json
dtlapse/iops/velvia.json
dtlapse/iops/vibrance.json
dtlapse/xmp/__init__.py
dtlapse/xmp/namespace.py
dtlapse-1.0.1.dist-info/LICENSE
dtlapse-1.0.1.dist-info/METADATA
dtlapse-1.0.1.dist-info/WHEEL
dtlapse-1.0.1.dist-info/entry_points.txt
dtlapse-1.0.1.dist-info/top_level.txt
dtlapse-1.0.1.dist-info/RECORD
