Metadata-Version: 2.1
Name: dtlapse
Version: 1.0.1
Summary: Create smooth timelapse videos with darktable
Home-page: https://gitlab.com/jochen.keil/dtlapse
Author: Jochen Keil
Author-email: jochen.keil@gmail.com
License: UNKNOWN
Platform: UNKNOWN
Classifier: Programming Language :: Python :: 3
Classifier: License :: OSI Approved :: GNU General Public License v3 or later (GPLv3+)
Classifier: Operating System :: OS Independent
Classifier: Topic :: Artistic Software
Classifier: Topic :: Multimedia
Classifier: Topic :: Multimedia :: Video
Requires-Python: >=3
Requires-Dist: attrdict (>=2.0.1)
Requires-Dist: matplotlib (>=3.1.1)
Requires-Dist: numpy (>=1.16.4)
Requires-Dist: scipy (>=1.3.0)
